wernstrom/__init__.py
wernstrom/download.py
wernstrom/raw_data.py
wernstrom/utils.py
wernstrom-0.4.4.dist-info/LICENSE
wernstrom-0.4.4.dist-info/WHEEL
wernstrom-0.4.4.dist-info/METADATA
wernstrom-0.4.4.dist-info/RECORD
