Metadata-Version: 2.1
Name: wernstrom
Version: 0.4.4
Summary: A minimal set of tools for working with the KITTI dataset in Python
Home-page: https://pypi.org/project/wernstrom/
License: MIT
Keywords: numpy,camera,kitti,data,robotics,vision,image processing
Author: walchko
Author-email: walchko@users.noreply.github.com
Requires-Python: >=3.8
Classifier: Development Status :: 4 - Beta
Classifier: Intended Audience :: Developers
Classifier: License :: OSI Approved :: MIT License
Classifier: Operating System :: OS Independent
Classifier: Programming Language :: Python :: 3
Classifier: Programming Language :: Python :: 3.10
Classifier: Programming Language :: Python :: 3.8
Classifier: Programming Language :: Python :: 3.9
Classifier: Topic :: Software Development :: Libraries
Classifier: Topic :: Software Development :: Libraries :: Application Frameworks
Classifier: Topic :: Software Development :: Libraries :: Python Modules
Requires-Dist: numpy
Requires-Dist: pillow
Requires-Dist: squaternion
Project-URL: Repository, https://github.com/MomsFriendlyRobotCompany/wernstrom
